pulumiverse_acme/__init__.py
pulumiverse_acme/_inputs.py
pulumiverse_acme/_utilities.py
pulumiverse_acme/certificate.py
pulumiverse_acme/get_server_url.py
pulumiverse_acme/outputs.py
pulumiverse_acme/provider.py
pulumiverse_acme/pulumi-plugin.json
pulumiverse_acme/py.typed
pulumiverse_acme/registration.py
pulumiverse_acme/config/__init__.py
pulumiverse_acme/config/__init__.pyi
pulumiverse_acme/config/vars.py
pulumiverse_acme-0.14.0.dist-info/METADATA
pulumiverse_acme-0.14.0.dist-info/WHEEL
pulumiverse_acme-0.14.0.dist-info/top_level.txt
pulumiverse_acme-0.14.0.dist-info/RECORD
